README.md
setup.py
py_nsbcli/__init__.py
py_nsbcli/config.py
py_nsbcli.egg-info/PKG-INFO
py_nsbcli.egg-info/SOURCES.txt
py_nsbcli.egg-info/dependency_links.txt
py_nsbcli.egg-info/requires.txt
py_nsbcli.egg-info/top_level.txt
py_nsbcli/isc/__init__.py
py_nsbcli/isc/contract.py
py_nsbcli/isc/transaction_intent.py
py_nsbcli/modules/__init__.py
py_nsbcli/modules/admin.py
py_nsbcli/modules/client.py
py_nsbcli/modules/contract.py
py_nsbcli/modules/kvdb.py
py_nsbcli/query/__init__.py
py_nsbcli/query/query.py
py_nsbcli/system_action/__init__.py
py_nsbcli/system_action/action.py
py_nsbcli/system_action/contract.py
py_nsbcli/system_merkle_proof/__init__.py
py_nsbcli/system_merkle_proof/contract.py
py_nsbcli/system_merkle_proof/merkle_proof.py
py_nsbcli/system_token/__init__.py
py_nsbcli/system_token/contract.py
py_nsbcli/types/__init__.py
py_nsbcli/types/transaction_header.py
py_nsbcli/types/wallet.py
py_nsbcli/util/__init__.py
py_nsbcli/util/cast.py
py_nsbcli/util/gojson.py
py_nsbcli/util/gotypes.py
py_nsbcli/util/util.py