Metadata-Version: 1.2
Name: py-nsbcli
Version: 0.5.20
Summary: interacting with Tendermint-NSB from python
Home-page: https://github.com/Myriad-Dreamin/py-nsbcli
Author: Myriad Dreamin
Author-email: xyangxi5@gmail.com
Maintainer: Myriad-Dreamin
Maintainer-email: xyangxi5@gmail.com
License: BSD 3-Clause "New" or "Revised" License
Platform: MacOS
Platform: Windows
Classifier: Development Status :: 2 - Pre-Alpha
Classifier: Operating System :: MacOS
Classifier: Operating System :: Microsoft :: Windows :: Windows 10
Classifier: Intended Audience :: Developers
Classifier: Topic :: Utilities
Classifier: Topic :: Software Development :: Libraries :: Python Modules
Classifier: License :: OSI Approved :: BSD License
Classifier: Natural Language :: Chinese (Simplified)
Classifier: Natural Language :: English
Classifier: Programming Language :: C
Classifier: Programming Language :: Python
Classifier: Programming Language :: Python :: Implementation
Classifier: Programming Language :: Python :: 3.7
